{
    "name": "DiarioTags",
    "fields": [
        {
            "fieldName": "nome",
            "fieldType": "String",
            "fieldValidateRules": [
                "required",
                "maxlength"
            ],
            "fieldValidateRulesMaxlength": "45"
        },
        {
            "fieldName": "idPai",
            "fieldType": "Integer"
        },
        {
            "fieldName": "nomeId",
            "fieldType": "String",
            "fieldValidateRules": [
                "maxlength"
            ],
            "fieldValidateRulesMaxlength": "45"
        },
        {
            "fieldName": "ativo",
            "fieldType": "Integer"
        }
    ],
    "relationships": [],
    "changelogDate": "20200508222000",
    "entityTableName": "diario_tags",
    "dto": "mapstruct",
    "pagination": "pagination",
    "service": "serviceClass",
    "jpaMetamodelFiltering": true,
    "fluentMethods": true,
    "readOnly": false,
    "embedded": false,
    "clientRootFolder": "",
    "applications": "*"
}