{
    "name": "LogUserFranquia",
    "fields": [
        {
            "fieldName": "descricao",
            "fieldType": "byte[]",
            "fieldTypeBlobContent": "text"
        }
    ],
    "relationships": [],
    "changelogDate": "20200508160600",
    "entityTableName": "log_user_franquia",
    "dto": "mapstruct",
    "pagination": "pagination",
    "service": "serviceClass",
    "jpaMetamodelFiltering": true,
    "fluentMethods": true,
    "readOnly": false,
    "embedded": false,
    "clientRootFolder": "",
    "applications": "*"
}