{
    "name": "Paciente",
    "fields": [
        {
            "fieldName": "idUnidade",
            "fieldType": "String",
            "fieldValidateRules": [
                "required"
            ]
        },
        {
            "fieldName": "idFranquia",
            "fieldType": "String"
        },
        {
            "fieldName": "idCidade",
            "fieldType": "String"
        },
        {
            "fieldName": "idCidadeFamiliar",
            "fieldType": "String"
        },
        {
            "fieldName": "idGrauParentesco",
            "fieldType": "Integer",
            "fieldValidateRules": [
                "required"
            ]
        },
        {
            "fieldName": "senha",
            "fieldType": "String",
            "fieldValidateRules": [
                "maxlength"
            ],
            "fieldValidateRulesMaxlength": "100"
        },
        {
            "fieldName": "nome",
            "fieldType": "String",
            "fieldValidateRules": [
                "maxlength"
            ],
            "fieldValidateRulesMaxlength": "60"
        },
        {
            "fieldName": "email",
            "fieldType": "String",
            "fieldValidateRules": [
                "maxlength"
            ],
            "fieldValidateRulesMaxlength": "100"
        },
        {
            "fieldName": "cpf",
            "fieldType": "String",
            "fieldValidateRules": [
                "maxlength"
            ],
            "fieldValidateRulesMaxlength": "20"
        },
        {
            "fieldName": "rg",
            "fieldType": "String",
            "fieldValidateRules": [
                "maxlength"
            ],
            "fieldValidateRulesMaxlength": "30"
        },
        {
            "fieldName": "registro",
            "fieldType": "String",
            "fieldValidateRules": [
                "maxlength"
            ],
            "fieldValidateRulesMaxlength": "50"
        },
        {
            "fieldName": "nascimento",
            "fieldType": "LocalDate"
        },
        {
            "fieldName": "sexo",
            "fieldType": "Integer"
        },
        {
            "fieldName": "telefone",
            "fieldType": "String",
            "fieldValidateRules": [
                "maxlength"
            ],
            "fieldValidateRulesMaxlength": "20"
        },
        {
            "fieldName": "telefone2",
            "fieldType": "String",
            "fieldValidateRules": [
                "maxlength"
            ],
            "fieldValidateRulesMaxlength": "20"
        },
        {
            "fieldName": "celular",
            "fieldType": "String",
            "fieldValidateRules": [
                "maxlength"
            ],
            "fieldValidateRulesMaxlength": "20"
        },
        {
            "fieldName": "celular1",
            "fieldType": "String",
            "fieldValidateRules": [
                "maxlength"
            ],
            "fieldValidateRulesMaxlength": "20"
        },
        {
            "fieldName": "cep",
            "fieldType": "String",
            "fieldValidateRules": [
                "maxlength"
            ],
            "fieldValidateRulesMaxlength": "10"
        },
        {
            "fieldName": "endereco",
            "fieldType": "String",
            "fieldValidateRules": [
                "maxlength"
            ],
            "fieldValidateRulesMaxlength": "100"
        },
        {
            "fieldName": "numero",
            "fieldType": "String",
            "fieldValidateRules": [
                "maxlength"
            ],
            "fieldValidateRulesMaxlength": "30"
        },
        {
            "fieldName": "complemento",
            "fieldType": "String",
            "fieldValidateRules": [
                "maxlength"
            ],
            "fieldValidateRulesMaxlength": "20"
        },
        {
            "fieldName": "bairro",
            "fieldType": "String",
            "fieldValidateRules": [
                "maxlength"
            ],
            "fieldValidateRulesMaxlength": "40"
        },
        {
            "fieldName": "cidade",
            "fieldType": "String",
            "fieldValidateRules": [
                "maxlength"
            ],
            "fieldValidateRulesMaxlength": "100"
        },
        {
            "fieldName": "uf",
            "fieldType": "String",
            "fieldValidateRules": [
                "maxlength"
            ],
            "fieldValidateRulesMaxlength": "5"
        },
        {
            "fieldName": "latitude",
            "fieldType": "String",
            "fieldValidateRules": [
                "maxlength"
            ],
            "fieldValidateRulesMaxlength": "60"
        },
        {
            "fieldName": "longitude",
            "fieldType": "String",
            "fieldValidateRules": [
                "maxlength"
            ],
            "fieldValidateRulesMaxlength": "60"
        },
        {
            "fieldName": "responsavelFamiliar",
            "fieldType": "String",
            "fieldValidateRules": [
                "maxlength"
            ],
            "fieldValidateRulesMaxlength": "60"
        },
        {
            "fieldName": "emailFamiliar",
            "fieldType": "String",
            "fieldValidateRules": [
                "maxlength"
            ],
            "fieldValidateRulesMaxlength": "100"
        },
        {
            "fieldName": "cpfFamiliar",
            "fieldType": "String",
            "fieldValidateRules": [
                "maxlength"
            ],
            "fieldValidateRulesMaxlength": "20"
        },
        {
            "fieldName": "rgFamiliar",
            "fieldType": "String",
            "fieldValidateRules": [
                "maxlength"
            ],
            "fieldValidateRulesMaxlength": "30"
        },
        {
            "fieldName": "nascimentoFamiliar",
            "fieldType": "LocalDate"
        },
        {
            "fieldName": "sexoFamiliar",
            "fieldType": "Integer"
        },
        {
            "fieldName": "telefoneFamiliar",
            "fieldType": "String",
            "fieldValidateRules": [
                "maxlength"
            ],
            "fieldValidateRulesMaxlength": "20"
        },
        {
            "fieldName": "telefone2Familiar",
            "fieldType": "String",
            "fieldValidateRules": [
                "maxlength"
            ],
            "fieldValidateRulesMaxlength": "20"
        },
        {
            "fieldName": "celularFamiliar",
            "fieldType": "String",
            "fieldValidateRules": [
                "maxlength"
            ],
            "fieldValidateRulesMaxlength": "20"
        },
        {
            "fieldName": "celular2Familiar",
            "fieldType": "String",
            "fieldValidateRules": [
                "maxlength"
            ],
            "fieldValidateRulesMaxlength": "20"
        },
        {
            "fieldName": "cepFamiliar",
            "fieldType": "String",
            "fieldValidateRules": [
                "maxlength"
            ],
            "fieldValidateRulesMaxlength": "10"
        },
        {
            "fieldName": "enderecoFamiliar",
            "fieldType": "String",
            "fieldValidateRules": [
                "maxlength"
            ],
            "fieldValidateRulesMaxlength": "100"
        },
        {
            "fieldName": "numeroFamiliar",
            "fieldType": "String",
            "fieldValidateRules": [
                "maxlength"
            ],
            "fieldValidateRulesMaxlength": "30"
        },
        {
            "fieldName": "complementoFamiliar",
            "fieldType": "String",
            "fieldValidateRules": [
                "maxlength"
            ],
            "fieldValidateRulesMaxlength": "20"
        },
        {
            "fieldName": "bairroFamiliar",
            "fieldType": "String",
            "fieldValidateRules": [
                "maxlength"
            ],
            "fieldValidateRulesMaxlength": "40"
        },
        {
            "fieldName": "cidadeFamiliar",
            "fieldType": "String",
            "fieldValidateRules": [
                "maxlength"
            ],
            "fieldValidateRulesMaxlength": "100"
        },
        {
            "fieldName": "ufFamiliar",
            "fieldType": "String",
            "fieldValidateRules": [
                "maxlength"
            ],
            "fieldValidateRulesMaxlength": "5"
        },
        {
            "fieldName": "latitudeFamiliar",
            "fieldType": "String",
            "fieldValidateRules": [
                "maxlength"
            ],
            "fieldValidateRulesMaxlength": "60"
        },
        {
            "fieldName": "longitudeFamiliar",
            "fieldType": "String",
            "fieldValidateRules": [
                "maxlength"
            ],
            "fieldValidateRulesMaxlength": "60"
        },
        {
            "fieldName": "observacao",
            "fieldType": "String",
            "fieldValidateRules": [
                "maxlength"
            ],
            "fieldValidateRulesMaxlength": "255"
        },
        {
            "fieldName": "aph",
            "fieldType": "Integer",
            "fieldValidateRules": [
                "required"
            ]
        },
        {
            "fieldName": "nivelComplexidade",
            "fieldType": "Integer"
        },
        {
            "fieldName": "passagemPs",
            "fieldType": "Integer"
        },
        {
            "fieldName": "obsPs",
            "fieldType": "String",
            "fieldValidateRules": [
                "maxlength"
            ],
            "fieldValidateRulesMaxlength": "255"
        },
        {
            "fieldName": "passagemInternacao",
            "fieldType": "Integer"
        },
        {
            "fieldName": "obsInternacao",
            "fieldType": "String",
            "fieldValidateRules": [
                "maxlength"
            ],
            "fieldValidateRulesMaxlength": "255"
        },
        {
            "fieldName": "custoTotal",
            "fieldType": "Float"
        },
        {
            "fieldName": "observacaoFamiliar",
            "fieldType": "String",
            "fieldValidateRules": [
                "maxlength"
            ],
            "fieldValidateRulesMaxlength": "255"
        },
        {
            "fieldName": "mesmoEndereco",
            "fieldType": "Integer"
        },
        {
            "fieldName": "acessoFamiliar",
            "fieldType": "Integer"
        },
        {
            "fieldName": "comResponsavel",
            "fieldType": "Integer"
        },
        {
            "fieldName": "cadastroCompleto",
            "fieldType": "Integer"
        },
        {
            "fieldName": "ativo",
            "fieldType": "Integer"
        },
        {
            "fieldName": "dataPost",
            "fieldType": "Instant",
            "fieldValidateRules": [
                "required"
            ]
        },
        {
            "fieldName": "detalhes",
            "fieldType": "String",
            "fieldValidateRules": [
                "maxlength"
            ],
            "fieldValidateRulesMaxlength": "255"
        },
        {
            "fieldName": "tipohospital",
            "fieldType": "Integer"
        },
        {
            "fieldName": "liminar",
            "fieldType": "String",
            "fieldValidateRules": [
                "maxlength"
            ],
            "fieldValidateRulesMaxlength": "50"
        },
        {
            "fieldName": "expoToken",
            "fieldType": "String",
            "fieldValidateRules": [
                "maxlength"
            ],
            "fieldValidateRulesMaxlength": "255"
        },
        {
            "fieldName": "profissionalPref",
            "fieldType": "Integer"
        },
        {
            "fieldName": "senhaChat",
            "fieldType": "String",
            "fieldValidateRules": [
                "maxlength"
            ],
            "fieldValidateRulesMaxlength": "45"
        }
    ],
    "relationships": [
        {
            "relationshipType": "one-to-many",
            "otherEntityName": "atendimento",
            "otherEntityRelationshipName": "idPaciente",
            "relationshipName": "atendimento"
        },
        {
            "relationshipType": "one-to-many",
            "otherEntityName": "atendimentoAssinaturas",
            "otherEntityRelationshipName": "idPaciente",
            "relationshipValidateRules": "required",
            "relationshipName": "atendimentoAssinaturas"
        },
        {
            "relationshipType": "one-to-many",
            "otherEntityName": "diario",
            "otherEntityRelationshipName": "idPaciente",
            "relationshipName": "diario"
        },
        {
            "relationshipType": "one-to-many",
            "otherEntityName": "pacienteDadosCartao",
            "otherEntityRelationshipName": "idPaciente",
            "relationshipName": "pacienteDadosCartao"
        },
        {
            "relationshipType": "one-to-many",
            "otherEntityName": "pacienteDiagnostico",
            "otherEntityRelationshipName": "idPaciente",
            "relationshipName": "pacienteDiagnostico"
        },
        {
            "relationshipType": "one-to-many",
            "otherEntityName": "pacienteDiario",
            "otherEntityRelationshipName": "idPaciente",
            "relationshipName": "pacienteDiario"
        },
        {
            "relationshipType": "one-to-many",
            "otherEntityName": "pacienteEnqueteApp",
            "otherEntityRelationshipName": "idPaciente",
            "relationshipName": "pacienteEnqueteApp"
        },
        {
            "relationshipType": "one-to-many",
            "otherEntityName": "pacienteOperadora",
            "otherEntityRelationshipName": "idPaciente",
            "relationshipName": "pacienteOperadora"
        },
        {
            "relationshipType": "one-to-many",
            "otherEntityName": "pacientePedido",
            "otherEntityRelationshipName": "idPaciente",
            "relationshipName": "pacientePedido"
        },
        {
            "relationshipType": "one-to-many",
            "otherEntityName": "pacientePush",
            "otherEntityRelationshipName": "idPaciente",
            "relationshipName": "pacientePush"
        },
        {
            "relationshipType": "one-to-many",
            "otherEntityName": "pacienteStatusAtual",
            "otherEntityRelationshipName": "idPaciente",
            "relationshipName": "pacienteStatusAtual"
        },
        {
            "relationshipType": "one-to-many",
            "otherEntityName": "pad",
            "otherEntityRelationshipName": "idPaciente",
            "relationshipName": "pad"
        },
        {
            "relationshipType": "one-to-many",
            "otherEntityName": "questionarios",
            "otherEntityRelationshipName": "pacienteId",
            "relationshipValidateRules": "required",
            "relationshipName": "questionarios"
        }
    ],
    "changelogDate": "20200502235400",
    "entityTableName": "paciente",
    "dto": "mapstruct",
    "pagination": "pagination",
    "service": "serviceClass",
    "jpaMetamodelFiltering": true,
    "fluentMethods": true,
    "readOnly": false,
    "embedded": false,
    "clientRootFolder": "",
    "applications": "*"
}