{
    "name": "PacienteHospital",
    "fields": [
        {
            "fieldName": "servico",
            "fieldType": "String",
            "fieldValidateRules": [
                "maxlength"
            ],
            "fieldValidateRulesMaxlength": "40"
        },
        {
            "fieldName": "styleLabel",
            "fieldType": "String",
            "fieldValidateRules": [
                "maxlength"
            ],
            "fieldValidateRulesMaxlength": "40"
        }
    ],
    "relationships": [],
    "changelogDate": "20200503000700",
    "entityTableName": "paciente_hospital",
    "dto": "mapstruct",
    "pagination": "pagination",
    "service": "serviceClass",
    "jpaMetamodelFiltering": true,
    "fluentMethods": true,
    "readOnly": false,
    "embedded": false,
    "clientRootFolder": "",
    "applications": "*"
}